AUTHORS
MANIFEST.in
README
setup.py
django_weave.egg-info/PKG-INFO
django_weave.egg-info/SOURCES.txt
django_weave.egg-info/dependency_links.txt
django_weave.egg-info/not-zip-safe
django_weave.egg-info/top_level.txt
testproject/__init__.py
testproject/__init__.pyc
testproject/logger.conf
testproject/manage.py
testproject/settings.py
testproject/settings.pyc
testproject/test.db3
testproject/urls.py
testproject/urls.pyc
testproject/views.py
testproject/views.pyc
testproject/weave_server.py
testproject/weave_server_tester.py
testproject/templates/testproject/.tmp_url_info.html.65872~
testproject/templates/testproject/.tmp_url_info.html.87310~
testproject/templates/testproject/url_info.html
weave/__init__.py
weave/admin.py
weave/constants.py
weave/decorators.py
weave/models.py
weave/tests.py
weave/urls.py
weave/utils.py
weave/views/__init__.py
weave/views/misc.py
weave/views/sync.py
weave/views/user.py